Workbook

Sheet Raw Data
A1: Order ID | B1: Date | C1: Customer | D1: Region | E1: Product | F1: Category | G1: Quantity | H1: Unit Price | I1: Payment | J1: TOtal Sales
A2: ORD001 | B2: 46023 | C2: Ahmed | D2: Dubai | E2: Laptop | F2: Electronics | G2: 2 | H2: 3500 | I2: Card | J2: =G2*H2 -> 7000
A3: ORD002 | B3: 46024 | C3: Sara | D3: Sharjah | E3: Mouse | F3: Electronics | G3: 5 | H3: 80 | I3: Cash | J3: =G3*H3 -> 400
A4: ORD003 | B4: 46025 | C4: Omar | D4: Dubai | E4: Chair | F4: Furniture | G4: 3 | H4: 450 | I4: Card | J4: =G4*H4 -> 1350
A5: ORD004 | B5: 46026 | C5: Fatima | D5: Abu Dhabi | E5: Printer | F5: Electronics | G5: 2 | H5: 850 | I5: Bank Transfer | J5: =G5*H5 -> 1700
A6: ORD005 | B6: 46027 | C6: Noor | D6: Dubai | E6: Laptop | F6: Electronics | G6: 1 | H6: 3500 | I6: Card | J6: =G6*H6 -> 3500
A7: ORD006 | B7: 46028 | C7: Hassan | D7: Sharjah | E7: Desk | F7: Furniture | G7: 2 | H7: 1200 | I7: Cash | J7: =G7*H7 -> 2400
A8: ORD007 | B8: 46029 | C8: Mariam | D8: Dubai | E8: Monitor | F8: Electronics | G8: 3 | H8: 900 | I8: Card | J8: =G8*H8 -> 2700
A9: ORD008 | B9: 46030 | C9: Ali | D9: Abu Dhabi | E9: Chair | F9: Furniture | G9: 4 | H9: 450 | I9: Cash | J9: =G9*H9 -> 1800
A10: ORD009 | B10: 46031 | C10: Ahmed | D10: Dubai | E10: Printer | F10: Electronics | G10: 1 | H10: 850 | I10: Card | J10: =G10*H10 -> 850
A11: ORD010 | B11: 46032 | C11: Sara | D11: Sharjah | E11: Laptop | F11: Electronics | G11: 2 | H11: 3500 | I11: Bank Transfer | J11: =G11*H11 -> 7000

Sheet Cleaned Data
A1: Order ID | B1: Date | C1: Customer | D1: Region | E1: Product | F1: Category | G1: Quantity | H1: Unit Price | I1: Payment | J1: TOtal Sales | K1: Unit Cost | L1: Total Product Cost | M1: Profit | N1: Profit Margin
A2: ORD001 | B2: 46023 | C2: Ahmed | D2: Dubai | E2: Laptop | F2: Electronics | G2: 2 | H2: 3500 | I2: Card | J2: =G2*H2 -> 7000 | K2: =_xlfn.XLOOKUP(E2,'Product Costs'!$A$2:$A$7,'Product Costs'!$B$2:$B$7,"Not found") -> 2800 | L2: =G2*K2 -> 5600 | M2: =J2-L2 -> 1400 | N2: =M2/J2 -> 0.2
A3: ORD002 | B3: 46024 | C3: Sara | D3: Sharjah | E3: Mouse | F3: Electronics | G3: 5 | H3: 80 | I3: Cash | J3: =G3*H3 -> 400 | K3: =_xlfn.XLOOKUP(E3,'Product Costs'!$A$2:$A$7,'Product Costs'!$B$2:$B$7,"Not found") -> 45 | L3: =G3*K3 -> 225 | M3: =J3-L3 -> 175 | N3: =M3/J3 -> 0.4375
A4: ORD003 | B4: 46025 | C4: Omar | D4: Dubai | E4: Chair | F4: Furniture | G4: 3 | H4: 450 | I4: Card | J4: =G4*H4 -> 1350 | K4: =_xlfn.XLOOKUP(E4,'Product Costs'!$A$2:$A$7,'Product Costs'!$B$2:$B$7,"Not found") -> 250 | L4: =G4*K4 -> 750 | M4: =J4-L4 -> 600 | N4: =M4/J4 -> 0.44444444
A5: ORD004 | B5: 46026 | C5: Fatima | D5: Abu Dhabi | E5: Printer | F5: Electronics | G5: 2 | H5: 850 | I5: Bank Transfer | J5: =G5*H5 -> 1700 | K5: =_xlfn.XLOOKUP(E5,'Product Costs'!$A$2:$A$7,'Product Costs'!$B$2:$B$7,"Not found") -> 600 | L5: =G5*K5 -> 1200 | M5: =J5-L5 -> 500 | N5: =M5/J5 -> 0.29411765
A6: ORD005 | B6: 46027 | C6: Noor | D6: Dubai | E6: Laptop | F6: Electronics | G6: 1 | H6: 3500 | I6: Card | J6: =G6*H6 -> 3500 | K6: =_xlfn.XLOOKUP(E6,'Product Costs'!$A$2:$A$7,'Product Costs'!$B$2:$B$7,"Not found") -> 2800 | L6: =G6*K6 -> 2800 | M6: =J6-L6 -> 700 | N6: =M6/J6 -> 0.2
A7: ORD006 | B7: 46028 | C7: Hassan | D7: Sharjah | E7: Desk | F7: Furniture | G7: 2 | H7: 1200 | I7: Cash | J7: =G7*H7 -> 2400 | K7: =_xlfn.XLOOKUP(E7,'Product Costs'!$A$2:$A$7,'Product Costs'!$B$2:$B$7,"Not found") -> 750 | L7: =G7*K7 -> 1500 | M7: =J7-L7 -> 900 | N7: =M7/J7 -> 0.375
A8: ORD007 | B8: 46029 | C8: Mariam | D8: Dubai | E8: Monitor | F8: Electronics | G8: 3 | H8: 900 | I8: Card | J8: =G8*H8 -> 2700 | K8: =_xlfn.XLOOKUP(E8,'Product Costs'!$A$2:$A$7,'Product Costs'!$B$2:$B$7,"Not found") -> 550 | L8: =G8*K8 -> 1650 | M8: =J8-L8 -> 1050 | N8: =M8/J8 -> 0.38888889
A9: ORD008 | B9: 46030 | C9: Ali | D9: Abu Dhabi | E9: Chair | F9: Furniture | G9: 4 | H9: 450 | I9: Cash | J9: =G9*H9 -> 1800 | K9: =_xlfn.XLOOKUP(E9,'Product Costs'!$A$2:$A$7,'Product Costs'!$B$2:$B$7,"Not found") -> 250 | L9: =G9*K9 -> 1000 | M9: =J9-L9 -> 800 | N9: =M9/J9 -> 0.44444444
A10: ORD009 | B10: 46031 | C10: Ahmed | D10: Dubai | E10: Printer | F10: Electronics | G10: 1 | H10: 850 | I10: Card | J10: =G10*H10 -> 850 | K10: =_xlfn.XLOOKUP(E10,'Product Costs'!$A$2:$A$7,'Product Costs'!$B$2:$B$7,"Not found") -> 600 | L10: =G10*K10 -> 600 | M10: =J10-L10 -> 250 | N10: =M10/J10 -> 0.29411765
A11: ORD010 | B11: 46032 | C11: Sara | D11: Sharjah | E11: Laptop | F11: Electronics | G11: 2 | H11: 3500 | I11: Bank Transfer | J11: =G11*H11 -> 7000 | K11: =_xlfn.XLOOKUP(E11,'Product Costs'!$A$2:$A$7,'Product Costs'!$B$2:$B$7,"Not found") -> 2800 | L11: =G11*K11 -> 5600 | M11: =J11-L11 -> 1400 | N11: =M11/J11 -> 0.2

Sheet Product Costs
A1: Product | B1: Unit Cost
A2: Laptop | B2: 2800
A3: Mouse | B3: 45
A4: Chair | B4: 250
A5: Printer | B5: 600
A6: Desk | B6: 750
A7: Monitor | B7: 550

Sheet Analysis
A1: KPI | B1: Value | F1: Product | G1: Revenue | H1: Profit | I1: Profit Margin
A2: Total Revenue | B2: =SUM('Cleaned Data'!J2:J11) -> 28700 | F2: Laptop | G2: =SUMIF('Cleaned Data'!E2:E11,"Laptop",'Cleaned Data'!J2:J11) -> 17500 | H2: =SUMIF('Cleaned Data'!E2:E11,"Laptop",'Cleaned Data'!M2:M11) -> 3500 | I2: =H2/G2 -> 0.2
A3: Total Profit | B3: =SUM('Cleaned Data'!M2:M11) -> 7775 | F3: Mouse | G3: =SUMIF('Cleaned Data'!E2:E11,"Mouse",'Cleaned Data'!J2:J11) -> 400 | H3: =SUMIF('Cleaned Data'!E2:E11,"Mouse",'Cleaned Data'!M2:M11) -> 175 | I3: =H3/G3 -> 0.4375
A4: Overall Profit Margin | B4: =B3/B2 -> 0.27090592 | F4: Chair | G4: =SUMIF('Cleaned Data'!E2:E11,"Chair",'Cleaned Data'!J2:J11) -> 3150 | H4: =SUMIF('Cleaned Data'!E2:E11,"Chair",'Cleaned Data'!M2:M11) -> 1400 | I4: =H4/G4 -> 0.44444444
A5: Total Orders | B5: =COUNT('Cleaned Data'!J2:J11) -> 10 | F5: Printer | G5: =SUMIF('Cleaned Data'!E2:E11,"Printer",'Cleaned Data'!J2:J11) -> 2550 | H5: =SUMIF('Cleaned Data'!E2:E11,"Printer",'Cleaned Data'!M2:M11) -> 750 | I5: =H5/G5 -> 0.29411765
A6: Average Order Value | B6: =B2/B5 -> 2870 | F6: Desk | G6: =SUMIF('Cleaned Data'!E2:E11,"Desk",'Cleaned Data'!J2:J11) -> 2400 | H6: =SUMIF('Cleaned Data'!E2:E11,"Desk",'Cleaned Data'!M2:M11) -> 900 | I6: =H6/G6 -> 0.375
F7: Monitor | G7: =SUMIF('Cleaned Data'!E2:E11,"Monitor",'Cleaned Data'!J2:J11) -> 2700 | H7: =SUMIF('Cleaned Data'!E2:E11,"Monitor",'Cleaned Data'!M2:M11) -> 1050 | I7: =H7/G7 -> 0.38888889
A9: Region | B9: Revenue | C9: Profit | D9: Profit Margin
A10: Dubai | B10: =SUMIF('Cleaned Data'!D2:D11,"Dubai",'Cleaned Data'!L2:L11) -> 11400 | C10: =SUMIF('Cleaned Data'!D2:D11,"Dubai",'Cleaned Data'!M2:M11) -> 4000 | D10: =C10/B10 -> 0.35087719
A11: Sharjah | B11: =SUMIF('Cleaned Data'!D2:D11,"Sharjah",'Cleaned Data'!L2:L11) -> 7325 | C11: =SUMIF('Cleaned Data'!D2:D11,"Sharjah",'Cleaned Data'!M2:M11) -> 2475 | D11: =C11/B11 -> 0.33788396
A12: Abu Dhabi | B12: =SUMIF('Cleaned Data'!D2:D11,"Abu Dhabi",'Cleaned Data'!L2:L11) -> 2200 | C12: =SUMIF('Cleaned Data'!D2:D11,"Abu Dhabi",'Cleaned Data'!M2:M11) -> 1300 | D12: =C12/B12 -> 0.59090909
A15: Category | B15: Revenue | C15: Profit | D15: Profit Margin
A16: Electronics | B16: =SUMIF('Cleaned Data'!F2:F11,"Electronics",'Cleaned Data'!J2:J11) -> 23150 | C16: =SUMIF('Cleaned Data'!F2:F11,"Electronics",'Cleaned Data'!M2:M11) -> 5475 | D16: =C16/B16 -> 0.23650108
A17: Furniture | B17: =SUMIF('Cleaned Data'!F2:F11,"Furniture",'Cleaned Data'!J2:J11) -> 5550 | C17: =SUMIF('Cleaned Data'!F2:F11,"Furniture",'Cleaned Data'!M2:M11) -> 2300 | D17: =C17/B17 -> 0.41441441
A23: Rvenue by Region | C23: Revenue | E23: Profit by Region | G23: Profit
A24: Dubai | C24: =Analysis!B10 -> 11400 | E24: Dubai | G24: =Analysis!C10 -> 4000
A25: Sharjah | C25: =Analysis!B11 -> 7325 | E25: Sharjah | G25: =Analysis!C11 -> 2475
A26: Abu Dhabi | C26: =Analysis!B12 -> 2200 | E26: Abu Dhabi | G26: =Analysis!C12 -> 1300
A30: Revenue by Product | E30: Profit by Product | I30: Category Performance
A31: Laptop | B31: =Analysis!G2 -> 17500 | E31: Laptop | F31: =Analysis!H2 -> 3500 | I31: Electronics | K31: =Analysis!B16 -> 23150
A32: Mouse | B32: =Analysis!G3 -> 400 | E32: Mouse | F32: =Analysis!H3 -> 175 | I32: Furniture | K32: =Analysis!B17 -> 5550
A33: Chair | B33: =Analysis!G4 -> 3150 | E33: Chair | F33: =Analysis!H4 -> 1400
A34: Printer | B34: =Analysis!G5 -> 2550 | E34: Printer | F34: =Analysis!H5 -> 750
A35: Desk | B35: =Analysis!G6 -> 2400 | E35: Desk | F35: =Analysis!H6 -> 900
A36: Monitor | B36: =Analysis!G7 -> 2700 | E36: Monitor | F36: =Analysis!H7 -> 1050

Sheet Dashboard
B1: SALES & PROFIT PERFORMANCE DASHBOARD
B2: Total Revenue | D2: Total Profit | F2: Profit Margin | H2: Orders | J2: Average Order Value
B3: =Analysis!B2 -> 28700 | D3: =Analysis!B3 -> 7775 | F3: =Analysis!B4 -> 0.27090592 | H3: =Analysis!B5 -> 10 | J3: =Analysis!B6 -> 2870 | M3: Key Insights
M4: Revenue
M6: Dubai generated the highest regional revenue at AED 11,400.
M7: Laptop generated the highest product revenue at AED 17,500.
M8: Electronics generated AED 23,150 in revenue.
M10: Profitability
M12: Total profit was AED 7,775.
M13: Overall profit margin was 27.09%.
M14: Laptop generated the highest total profit at AED 3,500.
M15: Furniture had a higher category profit margin than Electronics.
L20: `

Sheet Recommandation
A2: Recommendation 1 — Laptop profitability
B4: Investigate laptop supplier and purchasing costs to determine whether a lower unit cost can improve the laptop profit margin while maintaining sales volume.
A6: Recommendation 2 — Furniture profitability
B8: Investigate which factors contribute to Furniture's higher profit margin and assess whether similar pricing or cost strategies could be applied to other products.
A10: Recommendation 3 — Regional performance
B12: Analyze the factors behind Dubai's stronger sales performance and investigate whether successful approaches can be tested in other regions.

Sheet Project Limitations
B1: Project Limitations
B3: 1. The dataset is a sample dataset and does not represent a real company's financial performance.
B4: 2. The dataset does not contain operating expenses, so the analysis cannot calculate true net profit.
B5: 3. Cash flow data is not available, so cash-flow analysis was not performed.
B6: 4. Customer retention and churn data are not available, so NRR/churn analysis was not performed.
B7: 5. Marketing expenditure and customer acquisition data are not available, so CAC cannot be calculated.
B8: 6. Some product-cost information may be incomplete, which can affect profit calculations.
B9: 7. The dataset covers a limited period, so it cannot establish long-term sales or growth trends.
B13: Project Summary
B15: This project demonstrates an end-to-end sales and profitability analysis using Excel. The dataset was structured and analyzed to evaluate revenue, product costs, profit, and profit margins across regions, categories, and products. An interactive dashboard was created to present key performance indicators and business insights to management. Based on the available data, recommendations were developed to identify areas that may require further investigation and potential improvement.
